{
	"items": [
		{
			"id": 403329,
			"goodsId": 403330,
			"styleId": 403329,
			"warehouseId": 1,
			"name": "倩碧活芯乳两支装",
			"pic": "http://pic.cdfgsanya.com/assets/upload/product/11e2121c79249b05a9a3460bb4e6eafe_400x400.jpg",
			"salesPrice": {
				"type": "0",
				"name": "免税价",
				"value": "482.0000",
				"isShowPrice": null
			},
			"contrastPrice": {
				"type": "4",
				"name": "市场价",
				"value": "630.0000",
				"isShowPrice": null
			},
			"browsingTime": "2019-05-21 11:37:28",
			"shelfStatus": 1,
			"count": 319,
			"isSellable": true,
			"brand": "倩碧",
			"brandEN": "CLINIQUE",
			"brandId": 248271
		}, {
			"id": 402801,
			"goodsId": 402802,
			"styleId": 402801,
			"warehouseId": 1,
			"name": "茱莉蔻玫瑰衡肤花卉水沁润限量版",
			"pic": "http://pic.cdfgsanya.com/assets/upload/product/c9d9799b5f2b5a802dcedd7a6b64d74b_400x400.jpg",
			"salesPrice": {
				"type": "0",
				"name": "免税价",
				"value": "413.0000",
				"isShowPrice": null
			},
			"contrastPrice": {
				"type": "4",
				"name": "市场价",
				"value": "600.0000",
				"isShowPrice": null
			},
			"browsingTime": "2019-05-21 11:37:28",
			"shelfStatus": 1,
			"count": 62,
			"isSellable": true,
			"brand": "茱莉蔻",
			"brandEN": "Jurlique",
			"brandId": 248307
		}, {
			"id": 402761,
			"goodsId": 402762,
			"styleId": 402761,
			"warehouseId": 1,
			"name": "天梭DRESS SPORT系列机械T050.207.11.117.05",
			"pic": "http://pic.cdfgsanya.com/assets/upload/product/3a87996a3c6a48cc00dd6ff698c5a1f2_400x400.JPG",
			"salesPrice": {
				"type": "0",
				"name": "免税价",
				"value": "4700.0000",
				"isShowPrice": null
			},
			"contrastPrice": {
				"type": "4",
				"name": "市场价",
				"value": "5600.0000",
				"isShowPrice": null
			},
			"browsingTime": "2019-05-21 11:37:28",
			"shelfStatus": 1,
			"count": 2,
			"isSellable": true,
			"brand": "天梭",
			"brandEN": "TISSOT",
			"brandId": 248458
		}, {
			"id": 400332,
			"goodsId": 400333,
			"styleId": 400332,
			"warehouseId": 1,
			"name": "资生堂新红妍肌活精华露 100ML",
			"pic": "http://pic.cdfgsanya.com/assets/upload/product/0ff301c6b4b43622223ad2ac1ab0fa1a_400x400.jpg",
			"salesPrice": {
				"type": "0",
				"name": "免税价",
				"value": "1136.0000",
				"isShowPrice": null
			},
			"contrastPrice": {
				"type": "4",
				"name": "市场价",
				"value": "1450.0000",
				"isShowPrice": null
			},
			"browsingTime": "2019-05-21 11:37:28",
			"shelfStatus": 1,
			"count": 207,
			"isSellable": true,
			"brand": "资生堂",
			"brandEN": "SHISEIDO",
			"brandId": 248268
		}, {
			"id": 285151,
			"goodsId": 285151,
			"styleId": 285151,
			"warehouseId": 1,
			"name": "黛珂紫苏精华水 150ML",
			"pic": "http://pic.cdfgsanya.com/assets/upload/product/601/603/225510/228586/228592/285151_1_pic400_8840.jpg",
			"salesPrice": {
				"type": "0",
				"name": "免税价",
				"value": "278.0000",
				"isShowPrice": null
			},
			"contrastPrice": {
				"type": "4",
				"name": "市场价",
				"value": "375.0000",
				"isShowPrice": null
			},
			"browsingTime": "2019-05-21 11:37:28",
			"shelfStatus": 1,
			"count": 131,
			"isSellable": true,
			"brand": "黛珂",
			"brandEN": "COSME DECORTE",
			"brandId": 248432
		}, {
			"id": 403460,
			"goodsId": 403461,
			"styleId": 403460,
			"warehouseId": 1,
			"name": "蒂芙尼浓情女士香水50ML",
			"pic": "http://pic.cdfgsanya.com/assets/upload/product/eaa4aa8d6995674a04b3710a0e35ce26_400x400.JPG",
			"salesPrice": {
				"type": "0",
				"name": "免税价",
				"value": "702.0000",
				"isShowPrice": null
			},
			"contrastPrice": {
				"type": "4",
				"name": "市场价",
				"value": "845.0000",
				"isShowPrice": null
			},
			"browsingTime": "2019-05-21 11:37:28",
			"shelfStatus": 1,
			"count": 8,
			"isSellable": true,
			"brand": "蒂芙尼",
			"brandEN": "TIFFANY&CO.",
			"brandId": 249131
		}
	],
	"total": 13,
	"page": 1,
	"nav":[{"id":225511,"name":"腕表"},{"id":228634,"name":"女士腕表"},{"id":228637,"name":"机械"},{"id":248458,"name":"TISSOT 天梭"},{"id":349745,"name":"天梭表Tourelles系列机械T099.207.22.118.01"}],
	"detail":{"id":349745,"name":"天梭表Tourelles系列机械T099.207.22.118.01","nameEN":"Tissot Chemin Des Tourelles Auto T0992072211801","brand":{"id":248458,"initial":"TIAN","name":"天梭","nameEN":"TISSOT","log":"http://pic.cdfgsanya.com/assets/upload/brandlogo/2016/10/14/20161014034429481.jpg","url":"","title":"","banner":"","country":{"name":"瑞士","nameEN":"SUI","log":"http://pic.cdfgsanya.com/assets/upload/country/365893c6266b1627095bd894541e74a9.png"},"productCount":70,"description":"天梭（TISSOT），瑞士卓越制表品牌，隶属于斯沃琪集团。对于天梭而言，“时间，随你掌控”不仅仅是一句广告词，它传递了天梭品牌的DNA ，天梭一直致力于将前沿科技与时尚设计在钟表制作中完美融合。TISSOT品牌设计理念崇尚本色、自然，以简约、精致、个性的风格还本归原，倡导现代衣着感观与精神体验的结合，产品兼备舒适、品味与体贴，深受广大消费者的喜爱。"},"pics":["http://pic.cdfgsanya.com/assets/upload/product/601/603/349745_1_pic500_4266.JPG","http://pic.cdfgsanya.com/assets/upload/product/601/603/349745_2_pic500_7680.JPG","http://pic.cdfgsanya.com/assets/upload/product/601/603/349745_3_pic500_591.JPG","http://pic.cdfgsanya.com/assets/upload/product/601/603/349745_4_pic500_8774.JPG","http://pic.cdfgsanya.com/assets/upload/product/601/603/349745_5_pic500_9528.JPG"],"description":"杜鲁尔经典系列钢带80机芯机械手表T099.207.22.118.01","details":"<div style=\"background:#fff; color:#666;font-size:12px;font-family:Arial, Helvetica, sans-serif, \" microsoft=\"\">\n    <!---- 产品描述 ---->\n    <div style=\"width:100%; height:40px; border-bottom:1px dashed #ddd; line-height:40px; margin:10px 0 0; color:#333; font-size:14px;\">\n        <span style=\" padding-left:10px;\">产品描述<em style=\"color:#ccc; padding-left:10px;  font-style:normal;\">PRODUCT DESCRIPTION</em></span>\n    </div>\n    <div style=\"text-align:center;\">\n        <img src=\"http://pic.cdfgsanya.com/assets/upload/2018/7/13/20180713040427656.jpg\" alt=\"\"/><br/><img src=\"http://pic.cdfgsanya.com/assets/upload/2018/7/13/20180713040449367.jpg\" alt=\"\"/><br/><img src=\"http://pic.cdfgsanya.com/assets/upload/2018/7/13/20180713040457991.jpg\" alt=\"\"/>\n    </div><!---- 注意事项 ---->\n    <div style=\"width:100%; height:40px; border-bottom:1px dashed #ddd; line-height:40px;  color:#333;font-size:14px;\">\n        <strong style=\" padding-left:10px;\">手表维护及保养常识</strong>\n    </div>\n    <div style=\"padding:10px;line-height:20px;\">\n        表壳和表带如帖身衣物，会直接接触人体皮肤，如不清洁污垢，则容易弄脏衣服袖口，也容易造成皮肤瘙痒、皮肤过敏，因此需要常保清洁。当你取下手表时，用柔软布料轻拭表身、表带及扣环等，可延长手表的寿命。此外，对于不同类型的手表，有着不同的保养原则。\n    </div>\n    <div style=\" width:100%;font-size:14px; font-weight:bold; color:#333; height:30px; line-height:30px; background:#f7f7f7;\">\n        <strong style=\"padding-left:10px;\">全自动机械表</strong>\n    </div>\n    <div style=\" padding:10px;line-height:20px;\">\n        1.新购的全自动机械表在一周内恐怕日间活动量不够，而导致走时不足，故建议晚间放下前，把手表以平常状态将其左右反复摇摆约1分钟或手动上弦20-30次，以补充上弦，确保走时正常。 <br/>2.按国家标准，一级机械手表的走时误差在&amp;plusmn;45秒/日以内。保证自动上链手表(自动机械表)持续运转，建议您每天佩戴手表的有效时间不低于8小时。请勿在手表显示晚上9点钟至凌晨3点钟时间内进行调校日期的操作，以免损坏手表机械系统。 <br/>3.机械表不使用时，建议每月手动上弦一次，防止表内机油凝固。首次使用或停止佩戴后重新使用时，需手动上弦20～30次。\n    </div>\n    <div style=\" width:100%;font-size:14px;font-weight:bold;color:#333; height:30px; line-height:30px;background:#f7f7f7;\">\n        <strong style=\"padding-left:10px;\">石英表</strong>\n    </div>\n    <div style=\" padding:10px;line-height:20px;\">\n        1.石英手表的电池用量通常在两年以上，如果打算在数周或月内将手表闲置不戴，建议将其收藏好之前将表冠拉出。此举将中断手表机芯的供电以便于延长电池使用寿命。当电池电量耗尽而手表停走时，应尽快送到指定的维修站进行检查，避免让没有电的电池长期留在表内引致机芯损坏。 <br/>2.在常温5℃-35℃的范围内，可稳定准确运作，走时精度每月&amp;plusmn;15秒左右，若温度超过50℃或低于-10℃时会导致手表略微走快活走慢，当恢复常温时，上述情况会好转。 <br/>3.石英两针表在调校时间时要调快一分钟，以补偿齿轮的间隙。\n    </div>\n    <div style=\" width:100%;font-size:14px;font-weight:bold; color:#333; height:30px; line-height:30px;background:#f7f7f7;\">\n        <strong style=\"padding-left:10px;\">日常注意事项：</strong>\n    </div>\n    <div style=\" padding:10px;line-height:20px;\">\n        1.机械表要避免接近磁场，例如：放在产生磁场的电器旁（手机）或有磁场的物体（麻将机、音响等电器）的旁边，都可能引起手表暂时性停走或不准。<br/>2.避免在洗热水澡时或煮蒸身体时佩戴使用，以免损坏。任何防水腕表都不能接触热水、水蒸气、洗衣液、香皂等物品，如碰水请及时擦干（不能让水一直停留在表上），请不要在水中进行按键操作。<br/>3.避免直接接触化学溶剂、化学材料或环境均会腐蚀外观件。<br/>4.硬金属、蓝宝石玻璃表镜虽然抗磨损、防划，但不宜磕碰、重压、重摔等不适当操作。<br/>5.手表的防水依靠表玻璃、后盖、表把等处的防水胶圈而达到相应的标准。30米防水：洗脸洗手。100米防水：游泳池及海水表面使用。200米防水：潜水表标准。200米以上：浮潜及深潜使用。\n    </div><!---- 品牌故事 ---->\n    <div style=\"width:100%; height:40px; border-bottom:1px dashed #ddd; line-height:40px;margin:10px 0 0; color:#333;font-ize:14px;\">\n        <span style=\" padding-left:10px;\">品牌故事<em style=\"color:#ccc; padding-left:10px; font-style:normal;\">BRAND INTRODUCTION</em></span>\n    </div>\n    <div style=\"width:100%; text-align:left;overflow:hidden;\">\n        <div style=\"margin:0;padding:10px;line-height:20px;\">\n            天梭（TISSOT），瑞士卓越制表品牌，隶属于斯沃琪集团。对于天梭而言，&quot;时间，随你掌控&quot;不仅仅是一句广告词，它传递了天梭品牌的DNA，天梭一直致力于将前沿科技与时尚设计在钟表制作中完美融合。TISSOT品牌设计理念崇尚本色、自然，以简约、精致、个性的风格还本归原，倡导现代衣着感观与精神体验的结合，产品兼备舒适、品味与体贴，深受广大消费者的喜爱。\n        </div>\n    </div>\n</div>\n<p>\n    <br/>\n</p>","detailsEN":"","faqs":[{"title":"常见问题","sections":[{"id":1028,"name":"Q：购买时间有什么要求吗？","content":"旅客购买免税品时间距离离岛时间不能超过<strong>30</strong>天。<br/>1.<strong>三亚凤凰机场</strong>，航班出发时间要求如下：<br/>00:00--10:00之间购买，<strong>当</strong>日16:00之后<br/>10:00--21:00之间购买，提前6小时下单<br/>21:00--00:00之间购买，<strong>次</strong>日16:00之后<br/>2.<strong>海口美兰机场、海口火车站</strong>，航班/火车出发时间要求如下：<br/>00:00--09:00之间购买，<strong>次</strong>日08:00之后<br/>09:00--21:00之间购买，<strong>次</strong>日08:00之后<br/>21:00--00:00之间购买，<strong>后</strong>天08:00之后<br/>3.<strong>琼海博鳌机场</strong>，航班出发时间要求如下：<br/>00:00--09:00之间购买，<strong>次</strong>日11:00之后<br/>09:00--21:00之间购买，<strong>次</strong>日11:00之后<br/>21:00--00:00之间购买，<strong>后</strong>天11:00之后<br/>4.<strong style=\"white-space: normal;\">新海港、秀英港</strong>，轮渡出发时间要求如下：<br style=\"white-space: normal;\"/>00:00--09:00之间购买，<strong style=\"white-space: normal;\">次</strong>日08:00之后<br style=\"white-space: normal;\"/>09:00--21:00之间购买，<strong style=\"white-space: normal;\">次</strong>日08:00之后<br style=\"white-space: normal;\"/>21:00--00:00之间购买，<strong style=\"white-space: normal;\">后</strong>天08:00之后","shortName":null},{"id":1035,"name":"Q：在官网购买免税品需要满足什么条件？","content":"<p><span style=\"font-family: 微软雅黑, \" microsoft=\"\" font-size:=\"\">年满16周岁的中国公民且需持有离岛但不离境的机票、火车票或轮渡船票。</span></p>","shortName":null},{"id":1036,"name":"Q：还没有订机票、火车票或轮渡船票，可以购买吗？","content":"<p><span style=\"font-family: 微软雅黑, \" microsoft=\"\" font-size:=\"\">不可以，根据离岛免税政策规定，必须持有正确的离岛航班信息、火车票或轮渡船票信息才能购买。</span></p>","shortName":null},{"id":1022,"name":"Q：飞机航班、火车车次或轮渡班次变更或改签，怎么办？","content":"<p><span style=\"font-family: 微软雅黑, \" microsoft=\"\" font-size:=\"\">若您乘坐的飞机航班、火车车次或轮渡班次变更或改签，请至少在原行程出发前24小时联系客服（400-699-6956）更改，否则可能导致您无法提货，只能申请退货。</span></p>","shortName":null},{"id":10003,"name":"Q：市场价、划线价、促销价指的是什么？","content":"1、<strong>市场价、划线价</strong>：商品展示的划线价或市场价可能是品牌官网价、品牌专柜价、有税零售价；由于地区、时间的差异性和市场行情波动，品牌官网价、品牌专柜价、商品吊牌价等可能会与您购物时展示的不一致，该价格仅供您参考。<p>2、<strong>促销价</strong>：如无特殊说明，促销价是在免税价基础上给予的优惠价格。如有疑问，您可以在购买前与客服联系。<br/></p><p>3、<strong>价格异常</strong>：因可能存在系统缓存、页面更新延迟等不确定性情况，导致价格显示异常，商品具体售价请以订单结算页价格为准。如您发现异常情况出现，请立即联系我们修正，以便您能顺利购物。<br/></p>","shortName":null},{"id":1037,"name":"Q：限购数量是怎么回事？","content":"<p><span style=\"font-family: 微软雅黑, \" microsoft=\"\" font-size:=\"\">国家规定每人每次购买免税品按照不同类别不得超出相应数量（例如化妆品12件、香水8件、手表、首饰6件、箱包、配饰4件，家用空气净化器2件等）。</span></p>","shortName":null},{"id":1057,"name":"Q：购物次数、限购额度是怎么回事？","content":"<p>﻿1、购物次数：离岛旅客不限购物次数。</p><p>2、限购额度：每个公历年内，单价人民币8000元以下商品，累计购物金额不超过人民币30000元（含30000元），此外，单价人民币8000元以上商品，每年限购2件，每人每次限购1件，并在扣减未使用的免税额后缴纳进境物品进口税（行邮税），最高扣减免税额度为8000元。</p><p>（PS.同一旅客在同一年度内乘飞机、乘火车和乘轮船免税购物金额合计计算，且不得超过离岛免税政策的额度限制规定。）</p>","shortName":null},{"id":1059,"name":"Q：不同免税店购买，免税额度是分别计算的吗？","content":"<p><span style=\"font-family: 微软雅黑, \" microsoft=\"\" font-size:=\"\">离岛一次，计一次购买次数，只要在离岛免税店购物，就会消耗本次购买机会的免税额度。飞机、火车和轮渡离岛限购额度与限购数量同享，购买免税品的限制以身份证计算，三种方式离岛均会消耗免税额度。</span></p>","shortName":null},{"id":1063,"name":"Q：官网购买后，怎么提货呢？","content":"<p><strong>1. 乘坐飞机离岛</strong>：在离岛机场隔离区cdf提货点取货，可直接带上飞机。<br/>（三亚凤凰机场在国内出发厅215号登机口对面；海口美兰机场在国内出发厅15号登机口旁；琼海博鳌机场在国内出发厅2楼1号登机口旁。）</p><p><strong>2. 乘坐火车离岛</strong>：<br/>从三亚、东方火车站出发：火车到达海口火车站后，在站台处三亚国际免税城提货点提货；<br/>从海口火车站出发：在海口火车站站内三亚国际免税城提货点提货。<br/><strong style=\"white-space: normal;\">3. 轮渡离岛</strong>：<br style=\"white-space: normal;\"/>从新海港出发：<br/>散客提货进入安检后右转5米免税店散客提货点处；<br/>自驾提货通过车辆检票口后行至小车安检站右转50米免税店自驾提货点处。</p><p>从秀英港出发：<br/>散客提货安检后左转免税店散客提货点处；<br/>自驾提货经3号门进入码头①可向左行驶至7--8号码头免税店提货点自驾窗口提货；②或经过5号门和8号门前往11号码头免税店自驾提货处。</p>","shortName":null},{"id":10005,"name":"Q：下单成功后会收到短信通知吗？","content":"<p>下单支付后，若订单成功您会收到由三亚国际免税城发出的下单成功的信息；若订单失败，系统也会短信提示您，为避免影响您的购物，请您及时关注我们的短信提醒，如有问题，可致电客服电话：400-699-6956，我们会竭诚为您服务。</p>","shortName":null},{"id":1065,"name":"Q：提货时需要出示哪些凭证？","content":"<p><span style=\"font-family: 微软雅黑, \" microsoft=\"\" font-size:=\"\">提货时出示提货人身份证、登机牌、火车票或轮渡船票。</span></p>","shortName":null},{"id":1067,"name":"Q：提货时间需要注意哪些？","content":"建议您在登机、火车或轮渡出发时间前60分钟，到达提货处提取商品，避免因高峰期排队等候而延误您的行程。","shortName":null},{"id":1061,"name":"Q：如何开具发票？","content":"购买免税商品，您在办理提货后，关注“cdf离岛免税一三亚国际免税城”官方微信公众号，进入菜单“我的服务--电子发票”自助开具电子发票。","shortName":null}]},{"title":"售后服务","sections":[{"id":1069,"name":"提货前退货","content":"<p><span style=\"color: rgb(102, 102, 102); font-family: arial, \" microsoft=\"\" font-size:=\"\" background-color:=\"\">1.如出现任何原因而导致您在提货点未能提货，按照国家对免税品管理的相关规定，一律以成交价格整包办理退货、退款手续。</span><br style=\"color: rgb(102, 102, 102); font-family: arial, \" microsoft=\"\" font-size:=\"\" white-space:=\"\" background-color:=\"\"/><span style=\"color: rgb(102, 102, 102); font-family: arial, \" microsoft=\"\" font-size:=\"\" background-color:=\"\">2.如您提货时发现部分商品质量有问题要求退货，因涉及免税品核销不能对一张提货联中的某个单品进行核销，不可只退部分商品，必须整单退货。</span><br style=\"color: rgb(102, 102, 102); font-family: arial, \" microsoft=\"\" font-size:=\"\" white-space:=\"\" background-color:=\"\"/><span style=\"color: rgb(102, 102, 102); font-family: arial, \" microsoft=\"\" font-size:=\"\" background-color:=\"\">您也可以直接致电客服400-699-6956取消订单，经由工作人员确认后，在15个工作日内全额退款。</span></p>","shortName":null},{"id":1071,"name":"提货后退货","content":"<p><span style=\"color: rgb(102, 102, 102); font-family: arial, \" microsoft=\"\" font-size:=\"\" background-color:=\"\">请您在办理提货手续前仔细检查商品外观，若当场验货时，发现商品残损、缺件，您可在提货处直接办理退货。</span><br style=\"color: rgb(102, 102, 102); font-family: arial, \" microsoft=\"\" font-size:=\"\" white-space:=\"\" background-color:=\"\"/><span style=\"color: rgb(102, 102, 102); font-family: arial, \" microsoft=\"\" font-size:=\"\" background-color:=\"\">当您确认商品无误并成功办理提货手续后，我们将不再承担除国家三包规定之外的任何责任。三包规定内的情况需您提供有效证明（发票、说明书、赠品、购物凭证），并经售后人员核查属实后，为您办理退货。</span><br style=\"color: rgb(102, 102, 102); font-family: arial, \" microsoft=\"\" font-size:=\"\" white-space:=\"\" background-color:=\"\"/><span style=\"color: rgb(102, 102, 102); font-family: arial, \" microsoft=\"\" font-size:=\"\" background-color:=\"\">以下情况的退货申请无法受理：</span><br style=\"color: rgb(102, 102, 102); font-family: arial, \" microsoft=\"\" font-size:=\"\" white-space:=\"\" background-color:=\"\"/><span style=\"color: rgb(102, 102, 102); font-family: arial, \" microsoft=\"\" font-size:=\"\" background-color:=\"\">1.过保商品（超过三包保修期的商品）。</span><br style=\"color: rgb(102, 102, 102); font-family: arial, \" microsoft=\"\" font-size:=\"\" white-space:=\"\" background-color:=\"\"/><span style=\"color: rgb(102, 102, 102); font-family: arial, \" microsoft=\"\" font-size:=\"\" background-color:=\"\">2.未经授权的维修、误用、碰撞、疏忽、滥用、进液、事故、改动、不正确的使用所造成的商品质量问题，或撕毁、涂改标贴、商品序号、防伪标记。</span><br style=\"color: rgb(102, 102, 102); font-family: arial, \" microsoft=\"\" font-size:=\"\" white-space:=\"\" background-color:=\"\"/><span style=\"color: rgb(102, 102, 102); font-family: arial, \" microsoft=\"\" font-size:=\"\" background-color:=\"\">3.商品三包凭证、发票缺失或涂改。</span><br style=\"color: rgb(102, 102, 102); font-family: arial, \" microsoft=\"\" font-size:=\"\" white-space:=\"\" background-color:=\"\"/><span style=\"color: rgb(102, 102, 102); font-family: arial, \" microsoft=\"\" font-size:=\"\" background-color:=\"\">4.密封产品原包装打开，一次性封贴或塑封破损（质量问题除外）。</span><br style=\"color: rgb(102, 102, 102); font-family: arial, \" microsoft=\"\" font-size:=\"\" white-space:=\"\" background-color:=\"\"/><span style=\"color: rgb(102, 102, 102); font-family: arial, \" microsoft=\"\" font-size:=\"\" background-color:=\"\">5.产品已使用，但非商品本身质量问题（如：对于颜色、外观、形状、气味、使用效果不满意、商品的正常损耗造成的任何损坏等问题）。</span><br style=\"color: rgb(102, 102, 102); font-family: arial, \" microsoft=\"\" font-size:=\"\" white-space:=\"\" background-color:=\"\"/><span style=\"color: rgb(102, 102, 102); font-family: arial, \" microsoft=\"\" font-size:=\"\" background-color:=\"\">6.其他依法不在退货范围内的。</span><br/></p>","shortName":null}]}],"buyReading":{"id":1055,"name":"温馨提示","content":"<p><span style=\"color: rgb(102, 102, 102); font-family: arial, \" microsoft=\"\" font-size:=\"\" background-color:=\"\">1.三亚国际免税城官方商城所售商品凭保卡可享受厂家提供的品牌联保服务或指定服务商联保服务。</span><br style=\"color: rgb(102, 102, 102); font-family: arial, \" microsoft=\"\" font-size:=\"\" white-space:=\"\"/><span style=\"color: rgb(102, 102, 102); font-family: arial, \" microsoft=\"\" font-size:=\"\" background-color:=\"\">2.因屏幕显示与实际商品可能存在色差，请以收到实际商品的颜色为准。</span><br style=\"color: rgb(102, 102, 102); font-family: arial, \" microsoft=\"\" font-size:=\"\" white-space:=\"\"/><span style=\"color: rgb(102, 102, 102); font-family: arial, \" microsoft=\"\" font-size:=\"\" background-color:=\"\">3.鉴于免税品的特殊性，商品一旦售出概不退、换货。如给您带来不便之处，敬请谅解。如遇质量问题产生的退货邮寄费，将由我们承担。</span><br style=\"color: rgb(102, 102, 102); font-family: arial, \" microsoft=\"\" font-size:=\"\" white-space:=\"\"/><span style=\"color: rgb(102, 102, 102); font-family: arial, \" microsoft=\"\" font-size:=\"\" background-color:=\"\">4.如您未经我司工作人员同意，擅自将商品退回，由此产生的一切风险均由您自行承担。对于邮件或包裹等物品的签收不视为我司对您退回的商品负有任何责任，必要时售后客服部有权处置您擅自退回的商品。</span><br style=\"color: rgb(102, 102, 102); font-family: arial, \" microsoft=\"\" font-size:=\"\" white-space:=\"\"/><span style=\"color: rgb(102, 102, 102); font-family: arial, \" microsoft=\"\" font-size:=\"\" background-color:=\"\">5.退货时须将附件、说明书、发票、购物凭证、包装、商品、赠品一并退回我司，方可办理退货手续。</span><br style=\"color: rgb(102, 102, 102); font-family: arial, \" microsoft=\"\" font-size:=\"\" white-space:=\"\"/><span style=\"color: rgb(102, 102, 102); font-family: arial, \" microsoft=\"\" font-size:=\"\" background-color:=\"\">6.三亚国际免税城官网商城秉承客户至上的服务理念，为您提供最优质的商品及服务。如所售商品因生产工艺或仓储物流原因，可能会存在出现商品破损的几率，如发现请您及时与我司客服中心400-699-6956联系，我司将竭诚为您处理相关事宜。对于任何欺诈性行为，三亚国际免税城官网商城将保留依法追究法律责任的权利。</span></p>","shortName":null},"brandRecommends":null,"isShowBrandInfo":false,"isShowBrand":false,"collect":false,"content":null,"properties":[{"title":"商品编码","val":"E528601"},{"title":"厂商货号","val":"T0992072211801"},{"title":"商品名称","val":"天梭Tourelles系列机械表"},{"title":"品牌名称","val":"TISSOT 天梭"},{"title":"品牌发源地","val":"瑞士"},{"title":"机芯类型","val":"自动机械"},{"title":"表盘形状","val":"圆形"},{"title":"表径","val":"32mm"},{"title":"表壳材质","val":"316L钢"},{"title":"表壳颜色","val":"玫瑰金色"},{"title":"表盘颜色","val":"珍珠贝母白"},{"title":"表镜材质","val":"蓝宝石水晶镜面"},{"title":"表带颜色","val":"银色"},{"title":"表带材质","val":"316L钢"},{"title":"表扣类型","val":"蝴蝶双按扣"},{"title":"防水","val":"50m"},{"title":"功能","val":"日期显示"},{"title":"有无保修卡","val":"有"},{"title":"适合人群","val":"女士"}],"defaultStyleId":349745,"styles":null,"styleDefines":null,"productCode":"E528601","smallPics":["http://pic.cdfgsanya.com/assets/upload/product/601/603/349745_1_pic100_4266.JPG","http://pic.cdfgsanya.com/assets/upload/product/601/603/349745_2_pic100_7680.JPG","http://pic.cdfgsanya.com/assets/upload/product/601/603/349745_3_pic100_591.JPG","http://pic.cdfgsanya.com/assets/upload/product/601/603/349745_4_pic100_8774.JPG","http://pic.cdfgsanya.com/assets/upload/product/601/603/349745_5_pic100_9528.JPG"],"largePics":["http://pic.cdfgsanya.com/assets/upload/product/601/603/349745_1_pic900_4266.JPG","http://pic.cdfgsanya.com/assets/upload/product/601/603/349745_2_pic900_7680.JPG","http://pic.cdfgsanya.com/assets/upload/product/601/603/349745_3_pic900_591.JPG","http://pic.cdfgsanya.com/assets/upload/product/601/603/349745_4_pic900_8774.JPG","http://pic.cdfgsanya.com/assets/upload/product/601/603/349745_5_pic900_9528.JPG"],"virtualCategoryName":null,"productTag":null,"badges":null},
	"data":{"id":349745,"styleId":349745,"salesPrice":{"type":0,"name":"免税价","value":"5700.0000"},"contrastPrice":null,"count":5,"saleCount":101,"isSellable":true,"sellerGoodRate":0.0,"isCollect":false,"limitNumber":6,"rules":[{"ruleId":597,"type":2,"label":"满减","ruleName":"此商品专享每满1000减60","topicUrl":"","topicTitle":"此商品专享每满1000减60","discountAmount":0}],"tags":null,"flashSale":null,"stockTips":"","remarkCount":0,"remarks":null,"notes":[],"warehouseAlias":null,"remarkTitle":"","freightDescription":null,"delivery":{"declare":"<strong>三亚</strong>  三亚凤凰机场离岛，至少提前6小时下单<br />\r\n<strong>海口</strong>  海口美兰机场离岛，至少提前1天下单<br />\r\n<strong>注：购买时间视下单时段而定，具体说明请查看详情。</strong> ","content":"<p><img src=\"http://pic.cdfgsanya.com/assets/upload/article/a932e4672cb86fa8dfe548afdddb767d.jpg\" title=\"a932e4672cb86fa8dfe548afdddb767d.jpg\"/></p>","declares":[{"name":"三亚","content":"从三亚凤凰机场离岛，至少提前6小时下单\r\n"},{"name":"海口","content":"从海口美兰机场离岛，至少提前1天下单"},{"name":"琼海","content":"从琼海博鳌机场离岛，至少提前1天下单"},{"name":"注：","content":"购买时间视下单时段而定，具体说明请查看详情"}]},"limitNumberDescription":"<p><span style=\"font-family: 微软雅黑, \" microsoft=\"\" font-size:=\"\"><strong>购物次数</strong><br/>离岛旅客不限购物次数。<br/><br/><strong>限购额度</strong><br/>每个公历年内，单价人民币8000元以下商品，每年累计购物金额最多不超过人民币30000元（含30000元），此外，单价人民币8000元以上商品，每年限购2件，每人每次限购1件，并在扣减未使用的免税额后缴纳进境物品进口税（行邮税），最高可扣减免税额度为8000元。<br/>（PS.同一旅客在同一年度内乘飞机、乘火车和乘轮船离岛的免税购物金额合计计算，且不得超过离岛免税政策的额度限制规定。）<br/><br/><strong>限购数量</strong><br/>各品类商品限购数量如下：<br/>化妆品12件，香水8件，手表首饰6件，笔6件，小皮件6件，箱包4件，皮带4件，眼镜（含太阳镜）4件，鞋4件，美容仪器4件，家用空气净化器2件等。</span></p><p class=\"MsoNormal\" style=\"text-align: center;\"><span style=\"font-family: 微软雅黑; font-size: 12pt;\"><o:p></o:p></span></p>"},
	"recommend":{"relateds":[{"id":349856,"defaultGoodsId":0,"name":"天梭表BALLADE III系列机械T108.208.22.117.01","brandId":248458,"brand":"天梭","brandEN":"TISSOT","pic":"http://pic.cdfgsanya.com/assets/upload/product/601/603/349856_1_pic400_991.JPG","stockTips":null,"salesCount":103,"reviewCount":0,"salesPrice":{"type":"0","name":"免税价","value":"7100.0000","isShowPrice":null},"marketPrice":null,"contrastPrice":null,"count":2,"isSellable":true,"sellerGoodRate":0.0,"colorStyleCount":0,"tags":null,"activityTags":null,"remark":null,"styleId":349856,"goodsId":349856,"warehouseId":1,"warehouseAlias":null,"badges":null,"sellingOutBeforeTip":null,"styleName":null,"shelfStatus":0,"sellCount":0,"virtualCategoryName":null,"styles":null,"styleDefines":null},{"id":280027,"defaultGoodsId":0,"name":"天梭表Le Locle系列机械T41.1.183.35","brandId":248458,"brand":"天梭","brandEN":"TISSOT","pic":"http://pic.cdfgsanya.com/assets/upload/product/601/603/225511/228635/228640/280027_1_pic400_2452.JPG","stockTips":null,"salesCount":103,"reviewCount":0,"salesPrice":{"type":"0","name":"免税价","value":"3850.0000","isShowPrice":null},"marketPrice":null,"contrastPrice":{"type":"4","name":"市场价","value":"4600.0000","isShowPrice":null},"count":3,"isSellable":true,"sellerGoodRate":0.0,"colorStyleCount":0,"tags":null,"activityTags":null,"remark":null,"styleId":280027,"goodsId":280027,"warehouseId":1,"warehouseAlias":null,"badges":null,"sellingOutBeforeTip":null,"styleName":null,"shelfStatus":0,"sellCount":0,"virtualCategoryName":null,"styles":null,"styleDefines":null},{"id":272263,"defaultGoodsId":0,"name":"天梭Le Locle系列机械表T41.1.183.34","brandId":248458,"brand":"天梭","brandEN":"TISSOT","pic":"http://pic.cdfgsanya.com/assets/upload/product/601/603/225511/228634/228637/272263_3789479_pic400_7504.JPG","stockTips":null,"salesCount":103,"reviewCount":0,"salesPrice":{"type":"0","name":"免税价","value":"3750.0000","isShowPrice":null},"marketPrice":null,"contrastPrice":null,"count":2,"isSellable":true,"sellerGoodRate":0.0,"colorStyleCount":0,"tags":null,"activityTags":null,"remark":null,"styleId":272263,"goodsId":272263,"warehouseId":1,"warehouseAlias":null,"badges":null,"sellingOutBeforeTip":null,"styleName":null,"shelfStatus":0,"sellCount":0,"virtualCategoryName":null,"styles":null,"styleDefines":null},{"id":402563,"defaultGoodsId":0,"name":"天梭表CDT系列机械T099.207.36.447.00","brandId":248458,"brand":"天梭","brandEN":"TISSOT","pic":"http://pic.cdfgsanya.com/assets/upload/product/ca8f09387a530aa90e6108a40448bf9e_400x400.JPG","stockTips":null,"salesCount":102,"reviewCount":0,"salesPrice":{"type":"0","name":"免税价","value":"5350.0000","isShowPrice":null},"marketPrice":null,"contrastPrice":{"type":"4","name":"市场价","value":"6450.0000","isShowPrice":null},"count":1,"isSellable":true,"sellerGoodRate":0.0,"colorStyleCount":0,"tags":null,"activityTags":null,"remark":null,"styleId":402563,"goodsId":402564,"warehouseId":1,"warehouseAlias":null,"badges":null,"sellingOutBeforeTip":null,"styleName":null,"shelfStatus":0,"sellCount":0,"virtualCategoryName":null,"styles":null,"styleDefines":null},{"id":289656,"defaultGoodsId":0,"name":"天梭表LE LOCLE系列机械T41.2.183.33","brandId":248458,"brand":"天梭","brandEN":"TISSOT","pic":"http://pic.cdfgsanya.com/assets/upload/product/601/603/225511/228634/228637/289656_1_pic400_2419.jpg","stockTips":null,"salesCount":101,"reviewCount":0,"salesPrice":{"type":"0","name":"免税价","value":"4400.0000","isShowPrice":null},"marketPrice":null,"contrastPrice":{"type":"4","name":"市场价","value":"5300.0000","isShowPrice":null},"count":3,"isSellable":true,"sellerGoodRate":0.0,"colorStyleCount":0,"tags":null,"activityTags":null,"remark":null,"styleId":289656,"goodsId":289656,"warehouseId":1,"warehouseAlias":null,"badges":null,"sellingOutBeforeTip":null,"styleName":null,"shelfStatus":0,"sellCount":0,"virtualCategoryName":null,"styles":null,"styleDefines":null},{"id":276401,"defaultGoodsId":0,"name":"天梭表Tourelles系列机械T0992072211800","brandId":248458,"brand":"天梭","brandEN":"TISSOT","pic":"http://pic.cdfgsanya.com/assets/upload/product/601/603/225511/228634/228637/276401_1_pic400_1909.JPG","stockTips":null,"salesCount":101,"reviewCount":0,"salesPrice":{"type":"0","name":"免税价","value":"5700.0000","isShowPrice":null},"marketPrice":null,"contrastPrice":null,"count":3,"isSellable":true,"sellerGoodRate":0.0,"colorStyleCount":0,"tags":null,"activityTags":null,"remark":null,"styleId":276401,"goodsId":276401,"warehouseId":1,"warehouseAlias":null,"badges":null,"sellingOutBeforeTip":null,"styleName":null,"shelfStatus":0,"sellCount":0,"virtualCategoryName":null,"styles":null,"styleDefines":null}],"samekinds":[{"id":349856,"defaultGoodsId":0,"name":"天梭表BALLADE III系列机械T108.208.22.117.01","brandId":248458,"brand":"天梭","brandEN":"TISSOT","pic":"http://pic.cdfgsanya.com/assets/upload/product/601/603/349856_1_pic400_991.JPG","stockTips":null,"salesCount":103,"reviewCount":0,"salesPrice":{"type":"0","name":"免税价","value":"7100.0000","isShowPrice":null},"marketPrice":null,"contrastPrice":null,"count":2,"isSellable":true,"sellerGoodRate":0.0,"colorStyleCount":0,"tags":null,"activityTags":null,"remark":null,"styleId":349856,"goodsId":349856,"warehouseId":1,"warehouseAlias":null,"badges":null,"sellingOutBeforeTip":null,"styleName":null,"shelfStatus":0,"sellCount":0,"virtualCategoryName":null,"styles":null,"styleDefines":null},{"id":272263,"defaultGoodsId":0,"name":"天梭Le Locle系列机械表T41.1.183.34","brandId":248458,"brand":"天梭","brandEN":"TISSOT","pic":"http://pic.cdfgsanya.com/assets/upload/product/601/603/225511/228634/228637/272263_3789479_pic400_7504.JPG","stockTips":null,"salesCount":103,"reviewCount":0,"salesPrice":{"type":"0","name":"免税价","value":"3750.0000","isShowPrice":null},"marketPrice":null,"contrastPrice":null,"count":2,"isSellable":true,"sellerGoodRate":0.0,"colorStyleCount":0,"tags":null,"activityTags":null,"remark":null,"styleId":272263,"goodsId":272263,"warehouseId":1,"warehouseAlias":null,"badges":null,"sellingOutBeforeTip":null,"styleName":null,"shelfStatus":0,"sellCount":0,"virtualCategoryName":null,"styles":null,"styleDefines":null},{"id":280027,"defaultGoodsId":0,"name":"天梭表Le Locle系列机械T41.1.183.35","brandId":248458,"brand":"天梭","brandEN":"TISSOT","pic":"http://pic.cdfgsanya.com/assets/upload/product/601/603/225511/228635/228640/280027_1_pic400_2452.JPG","stockTips":null,"salesCount":103,"reviewCount":0,"salesPrice":{"type":"0","name":"免税价","value":"3850.0000","isShowPrice":null},"marketPrice":null,"contrastPrice":{"type":"4","name":"市场价","value":"4600.0000","isShowPrice":null},"count":3,"isSellable":true,"sellerGoodRate":0.0,"colorStyleCount":0,"tags":null,"activityTags":null,"remark":null,"styleId":280027,"goodsId":280027,"warehouseId":1,"warehouseAlias":null,"badges":null,"sellingOutBeforeTip":null,"styleName":null,"shelfStatus":0,"sellCount":0,"virtualCategoryName":null,"styles":null,"styleDefines":null},{"id":402563,"defaultGoodsId":0,"name":"天梭表CDT系列机械T099.207.36.447.00","brandId":248458,"brand":"天梭","brandEN":"TISSOT","pic":"http://pic.cdfgsanya.com/assets/upload/product/ca8f09387a530aa90e6108a40448bf9e_400x400.JPG","stockTips":null,"salesCount":102,"reviewCount":0,"salesPrice":{"type":"0","name":"免税价","value":"5350.0000","isShowPrice":null},"marketPrice":null,"contrastPrice":{"type":"4","name":"市场价","value":"6450.0000","isShowPrice":null},"count":1,"isSellable":true,"sellerGoodRate":0.0,"colorStyleCount":0,"tags":null,"activityTags":null,"remark":null,"styleId":402563,"goodsId":402564,"warehouseId":1,"warehouseAlias":null,"badges":null,"sellingOutBeforeTip":null,"styleName":null,"shelfStatus":0,"sellCount":0,"virtualCategoryName":null,"styles":null,"styleDefines":null},{"id":276401,"defaultGoodsId":0,"name":"天梭表Tourelles系列机械T0992072211800","brandId":248458,"brand":"天梭","brandEN":"TISSOT","pic":"http://pic.cdfgsanya.com/assets/upload/product/601/603/225511/228634/228637/276401_1_pic400_1909.JPG","stockTips":null,"salesCount":101,"reviewCount":0,"salesPrice":{"type":"0","name":"免税价","value":"5700.0000","isShowPrice":null},"marketPrice":null,"contrastPrice":null,"count":3,"isSellable":true,"sellerGoodRate":0.0,"colorStyleCount":0,"tags":null,"activityTags":null,"remark":null,"styleId":276401,"goodsId":276401,"warehouseId":1,"warehouseAlias":null,"badges":null,"sellingOutBeforeTip":null,"styleName":null,"shelfStatus":0,"sellCount":0,"virtualCategoryName":null,"styles":null,"styleDefines":null},{"id":272264,"defaultGoodsId":0,"name":"天梭Le Locle系列机械表T41.2.183.34","brandId":248458,"brand":"天梭","brandEN":"TISSOT","pic":"http://pic.cdfgsanya.com/assets/upload/product/601/603/225511/228634/228637/272264_3789553_pic400_7059.JPG","stockTips":null,"salesCount":101,"reviewCount":0,"salesPrice":{"type":"0","name":"免税价","value":"4450.0000","isShowPrice":null},"marketPrice":null,"contrastPrice":null,"count":2,"isSellable":true,"sellerGoodRate":0.0,"colorStyleCount":0,"tags":null,"activityTags":null,"remark":null,"styleId":272264,"goodsId":272264,"warehouseId":1,"warehouseAlias":null,"badges":null,"sellingOutBeforeTip":null,"styleName":null,"shelfStatus":0,"sellCount":0,"virtualCategoryName":null,"styles":null,"styleDefines":null}],"maylikes":[{"id":289656,"defaultGoodsId":0,"name":"天梭表LE LOCLE系列机械T41.2.183.33","brandId":248458,"brand":"天梭","brandEN":"TISSOT","pic":"http://pic.cdfgsanya.com/assets/upload/product/601/603/225511/228634/228637/289656_1_pic400_2419.jpg","stockTips":null,"salesCount":0,"reviewCount":0,"salesPrice":{"type":"0","name":"免税价","value":"4400.0000","isShowPrice":null},"marketPrice":null,"contrastPrice":{"type":"4","name":"市场价","value":"5300.0000","isShowPrice":null},"count":3,"isSellable":true,"sellerGoodRate":0.0,"colorStyleCount":0,"tags":null,"activityTags":null,"remark":null,"styleId":289656,"goodsId":289656,"warehouseId":1,"warehouseAlias":null,"badges":null,"sellingOutBeforeTip":null,"styleName":null,"shelfStatus":0,"sellCount":0,"virtualCategoryName":null,"styles":null,"styleDefines":null},{"id":289201,"defaultGoodsId":0,"name":"天梭表Ballade系列机械T1082082211700","brandId":248458,"brand":"天梭","brandEN":"TISSOT","pic":"http://pic.cdfgsanya.com/assets/upload/product/601/603/225511/228634/228637/289201_1_pic400_8009.JPG","stockTips":null,"salesCount":0,"reviewCount":0,"salesPrice":{"type":"0","name":"免税价","value":"7100.0000","isShowPrice":null},"marketPrice":null,"contrastPrice":null,"count":0,"isSellable":false,"sellerGoodRate":0.0,"colorStyleCount":0,"tags":null,"activityTags":null,"remark":null,"styleId":289201,"goodsId":289201,"warehouseId":1,"warehouseAlias":null,"badges":null,"sellingOutBeforeTip":null,"styleName":null,"shelfStatus":0,"sellCount":0,"virtualCategoryName":null,"styles":null,"styleDefines":null},{"id":289202,"defaultGoodsId":0,"name":"天梭表Ballade系列机械T1082081111700","brandId":248458,"brand":"天梭","brandEN":"TISSOT","pic":"http://pic.cdfgsanya.com/assets/upload/product/601/603/225511/228634/228637/289202_1_pic400_7114.jpg","stockTips":null,"salesCount":0,"reviewCount":0,"salesPrice":{"type":"0","name":"免税价","value":"6400.0000","isShowPrice":null},"marketPrice":null,"contrastPrice":null,"count":0,"isSellable":false,"sellerGoodRate":0.0,"colorStyleCount":0,"tags":null,"activityTags":null,"remark":null,"styleId":289202,"goodsId":289202,"warehouseId":1,"warehouseAlias":null,"badges":null,"sellingOutBeforeTip":null,"styleName":null,"shelfStatus":0,"sellCount":0,"virtualCategoryName":null,"styles":null,"styleDefines":null},{"id":289446,"defaultGoodsId":0,"name":"天梭Lovely系列石英女表T058.009.33.031.01","brandId":248458,"brand":"天梭","brandEN":"TISSOT","pic":"http://pic.cdfgsanya.com/assets/upload/product/601/603/225511/228634/228636/289446_1_pic400_6591.JPG","stockTips":null,"salesCount":0,"reviewCount":0,"salesPrice":{"type":"0","name":"免税价","value":"2400.0000","isShowPrice":null},"marketPrice":null,"contrastPrice":{"type":"4","name":"市场价","value":"2890.0000","isShowPrice":null},"count":1,"isSellable":true,"sellerGoodRate":0.0,"colorStyleCount":0,"tags":null,"activityTags":null,"remark":null,"styleId":289446,"goodsId":289446,"warehouseId":1,"warehouseAlias":null,"badges":null,"sellingOutBeforeTip":null,"styleName":null,"shelfStatus":0,"sellCount":0,"virtualCategoryName":null,"styles":null,"styleDefines":null}],"recommendations":[{"id":275474,"defaultGoodsId":0,"name":"天梭Tourelles系列机械女表T099.207.11.118.00","brandId":248458,"brand":"天梭","brandEN":"TISSOT","pic":"http://pic.cdfgsanya.com/assets/upload/product/601/603/225511/228634/228637/275474_1_pic400_6963.JPG","stockTips":null,"salesCount":0,"reviewCount":0,"salesPrice":{"type":"0","name":"免税价","value":"5000.0000","isShowPrice":null},"marketPrice":null,"contrastPrice":null,"count":5,"isSellable":true,"sellerGoodRate":0.0,"colorStyleCount":0,"tags":null,"activityTags":null,"remark":null,"styleId":275474,"goodsId":275474,"warehouseId":1,"warehouseAlias":null,"badges":null,"sellingOutBeforeTip":null,"styleName":null,"shelfStatus":0,"sellCount":0,"virtualCategoryName":null,"styles":null,"styleDefines":null},{"id":272284,"defaultGoodsId":0,"name":"天梭Carson系列自动机械男表T085.407.16.013.00","brandId":248458,"brand":"天梭","brandEN":"TISSOT","pic":"http://pic.cdfgsanya.com/assets/upload/product/601/603/225511/228635/228640/272284_1_pic400_1399.jpg","stockTips":null,"salesCount":0,"reviewCount":0,"salesPrice":{"type":"0","name":"免税价","value":"3500.0000","isShowPrice":null},"marketPrice":null,"contrastPrice":{"type":"4","name":"市场价","value":"3890.0000","isShowPrice":null},"count":0,"isSellable":false,"sellerGoodRate":0.0,"colorStyleCount":0,"tags":null,"activityTags":null,"remark":null,"styleId":272284,"goodsId":272284,"warehouseId":1,"warehouseAlias":null,"badges":null,"sellingOutBeforeTip":null,"styleName":null,"shelfStatus":0,"sellCount":0,"virtualCategoryName":null,"styles":null,"styleDefines":null},{"id":272578,"defaultGoodsId":0,"name":"天梭Tradition系列石英表T063.617.36.037.00","brandId":248458,"brand":"天梭","brandEN":"TISSOT","pic":"http://pic.cdfgsanya.com/assets/upload/product/601/603/225511/228635/228639/272578_1_pic400_729.jpg","stockTips":null,"salesCount":0,"reviewCount":0,"salesPrice":{"type":"0","name":"免税价","value":"3100.0000","isShowPrice":null},"marketPrice":null,"contrastPrice":{"type":"4","name":"市场价","value":"3600.0000","isShowPrice":null},"count":2,"isSellable":true,"sellerGoodRate":0.0,"colorStyleCount":0,"tags":null,"activityTags":null,"remark":null,"styleId":272578,"goodsId":272578,"warehouseId":1,"warehouseAlias":null,"badges":null,"sellingOutBeforeTip":null,"styleName":null,"shelfStatus":0,"sellCount":0,"virtualCategoryName":null,"styles":null,"styleDefines":null},{"id":272585,"defaultGoodsId":0,"name":"天梭Carson系列机械女表T085.207.16.013.00","brandId":248458,"brand":"天梭","brandEN":"TISSOT","pic":"http://pic.cdfgsanya.com/assets/upload/product/601/603/225511/228634/228637/272585_1_pic400_5360.JPG","stockTips":null,"salesCount":0,"reviewCount":0,"salesPrice":{"type":"0","name":"免税价","value":"3500.0000","isShowPrice":null},"marketPrice":null,"contrastPrice":{"type":"4","name":"市场价","value":"3850.0000","isShowPrice":null},"count":1,"isSellable":true,"sellerGoodRate":0.0,"colorStyleCount":0,"tags":null,"activityTags":null,"remark":null,"styleId":272585,"goodsId":272585,"warehouseId":1,"warehouseAlias":null,"badges":null,"sellingOutBeforeTip":null,"styleName":null,"shelfStatus":0,"sellCount":0,"virtualCategoryName":null,"styles":null,"styleDefines":null}]}
}